tests/__init__.py
tests/test_formatter.py
ukraine_phone_formatter/__init__.py
ukraine_phone_formatter/formatter.py
ukraine_phone_formatter-0.1.0.dist-info/licenses/LICENSE
ukraine_phone_formatter-0.1.0.dist-info/METADATA
ukraine_phone_formatter-0.1.0.dist-info/WHEEL
ukraine_phone_formatter-0.1.0.dist-info/top_level.txt
ukraine_phone_formatter-0.1.0.dist-info/RECORD
