Metadata-Version: 2.4
Name: ukraine-phone-formatter
Version: 0.1.0
Summary: Ukraine Phone Formatter is a simple Python library that formats Ukrainian phone numbers into a readable and standardized format.
Home-page: https://github.com/stkossman/ukraine_phone_formatter_py
Author: Andrii Stavskyi
Author-email: Andrii Stavskyi <an.stawski@outlook.com>
License: MIT License
Classifier: Programming Language :: Python :: 3
Classifier: License :: OSI Approved :: MIT License
Classifier: Operating System :: OS Independent
Requires-Python: >=3.6
License-File: LICENSE
Dynamic: author
Dynamic: home-page
Dynamic: license-file
Dynamic: requires-python
